ipytoolbox/__init__.py
ipytoolbox/magics.py
ipytoolbox/version.py
ipytoolbox-0.3.0.dist-info/LICENSE
ipytoolbox-0.3.0.dist-info/METADATA
ipytoolbox-0.3.0.dist-info/WHEEL
ipytoolbox-0.3.0.dist-info/top_level.txt
ipytoolbox-0.3.0.dist-info/RECORD
