Metadata-Version: 2.1
Name: ipytoolbox
Version: 0.3.0
Summary: A collection of IPython magic commands and other utilities
Author-email: Carl Thomé <carlthome@gmail.com>
License: GNU AFFERO GENERAL PUBLIC LICENSE
Project-URL: Homepage, https://github.com/carlthome/ipytoolbox
Project-URL: Bugs, https://github.com/carlthome/ipytoolbox/issues
Requires-Python: >=3.8
License-File: LICENSE
Requires-Dist: ipython
Requires-Dist: matplotlib
Provides-Extra: notebooks
Requires-Dist: jupyter ; extra == 'notebooks'
Provides-Extra: tests
Requires-Dist: pytest ; extra == 'tests'
Requires-Dist: pytest-cov ; extra == 'tests'
